googlespy/__init__.py
googlespy/core.py
googlespy-1.1.1.dist-info/METADATA
googlespy-1.1.1.dist-info/WHEEL
googlespy-1.1.1.dist-info/top_level.txt
googlespy-1.1.1.dist-info/RECORD
