Metadata-Version: 2.1
Name: googlespy
Version: 1.1.1
Summary: A Python package to search Google and retrieve filtered links.
Home-page: https://mrfidal.in/py/package/googlespy
Author: Fidal
Author-email: mrfidal@proton.me
Keywords: mrfidal,fidal palamparambil,google,search,scraping,web scraping,python,googlesearch,api,filtered links,alpha
Classifier: Programming Language :: Python :: 3
Classifier: License :: OSI Approved :: MIT License
Classifier: Operating System :: OS Independent
Classifier: Intended Audience :: Developers
Classifier: Topic :: Software Development :: Libraries :: Python Modules
Requires-Python: >=3.6
Requires-Dist: requests
Requires-Dist: beautifulsoup4
